pyade/__init__.py
pyade/exception.py
pyade/version.py
pyade-0.0.2.dist-info/DESCRIPTION.rst
pyade-0.0.2.dist-info/entry_points.txt
pyade-0.0.2.dist-info/METADATA
pyade-0.0.2.dist-info/metadata.json
pyade-0.0.2.dist-info/RECORD
pyade-0.0.2.dist-info/top_level.txt
pyade-0.0.2.dist-info/WHEEL
