Metadata-Version: 2.0
Name: pyade
Version: 0.0.2
Summary: Python client for ADE web API
Home-page: https://github.com/scls19fr/pyade
Author: Sebastien Celles
Author-email: s.celles@gmail.com
License: GPL v3
Keywords: python ade client web api schedule scheduling software
Platform: UNKNOWN
Classifier: Development Status :: 3 - Alpha
Classifier: Environment :: Console
Classifier: Intended Audience :: Developers
Classifier: Operating System :: OS Independent
Classifier: Programming Language :: Cython
Classifier: Programming Language :: Python
Classifier: Programming Language :: Python :: 2.7
Classifier: Programming Language :: Python :: 3.3
Classifier: Programming Language :: Python :: 3.4
Classifier: Topic :: Office/Business :: Scheduling
Classifier: License :: OSI Approved :: GNU General Public License v3 or later (GPLv3+)
Requires-Dist: click
Requires-Dist: requests
Requires-Dist: pytz
Provides-Extra: dev
Requires-Dist: check-manifest; extra == 'dev'
Requires-Dist: nose; extra == 'dev'
Provides-Extra: test
Requires-Dist: coverage; extra == 'test'
Requires-Dist: nose; extra == 'test'
